pyorlib/__init__.py
pyorlib/algebra/__init__.py
pyorlib/algebra/element.py
pyorlib/algebra/expressions/__init__.py
pyorlib/algebra/expressions/expression.py
pyorlib/algebra/terms/__init__.py
pyorlib/algebra/terms/term.py
pyorlib/algebra/terms/constants/__init__.py
pyorlib/algebra/terms/constants/constant.py
pyorlib/algebra/terms/variables/__init__.py
pyorlib/algebra/terms/variables/variable.py
pyorlib/core/__init__.py
pyorlib/core/constants/__init__.py
pyorlib/core/constants/stdout_colors.py
pyorlib/core/exceptions/__init__.py
pyorlib/core/exceptions/pyorlib_exception.py
pyorlib/core/loggers/__init__.py
pyorlib/core/loggers/logger.py
pyorlib/core/loggers/stdout_logger.py
pyorlib/core/validators/__init__.py
pyorlib/core/validators/fields/__init__.py
pyorlib/core/validators/fields/field_validator.py
pyorlib/engines/__init__.py
pyorlib/engines/engine.py
pyorlib/engines/cplex/__init__.py
pyorlib/engines/cplex/cplex_engine.py
pyorlib/engines/gurobi/__init__.py
pyorlib/engines/gurobi/gurobi_engine.py
pyorlib/engines/ortools/__init__.py
pyorlib/engines/ortools/ortools_engine.py
pyorlib/engines/pulp/__init__.py
pyorlib/engines/pulp/pulp_engine.py
pyorlib/enums/__init__.py
pyorlib/enums/optimization_type.py
pyorlib/enums/parameter_type.py
pyorlib/enums/solution_status.py
pyorlib/enums/term_type.py
pyorlib/enums/value_type.py
pyorlib/exceptions/__init__.py
pyorlib/exceptions/cplex_exception.py
pyorlib/exceptions/gurobi_exception.py
pyorlib/exceptions/model_exception.py
pyorlib/exceptions/ortools_exception.py
pyorlib/exceptions/pulp_exception.py
pyorlib/exceptions/term_exception.py
pyorlib/model/__init__.py
pyorlib/model/model.py
pyorlib/structures/__init__.py
pyorlib/structures/definitions/__init__.py
pyorlib/structures/definitions/dimension_definition.py
pyorlib/structures/definitions/parameter_definition.py
pyorlib/structures/definitions/term_definition.py
pyorlib/structures/parameters/__init__.py
pyorlib/structures/parameters/multi_value_parameter.py
pyorlib-0.1.3.dist-info/METADATA
pyorlib-0.1.3.dist-info/WHEEL
pyorlib-0.1.3.dist-info/licenses/LICENSE
pyorlib-0.1.3.dist-info/RECORD
