Metadata-Version: 2.4
Name: pyorlib
Version: 0.1.3
Summary: A powerful Python library for operations research. Define, solve, and interact with mathematical models in a standardized manner across different optimization packages.
Project-URL: Homepage, https://github.com/dapensoft/pyorlib
Project-URL: Documentation, https://dapensoft.github.io/pyorlib/
Project-URL: Repository, https://github.com/dapensoft/pyorlib
Project-URL: Changelog, https://dapensoft.github.io/pyorlib/release-notes
Author-email: Isaac Da Pena <dapensoft@gmail.com>, Manuel Da Pena <dapensoft@gmail.com>
License-Expression: MIT
License-File: LICENSE
Keywords: operation-research,optimization,optimization-modeling,python
Classifier: Intended Audience :: Developers
Classifier: Intended Audience :: Education
Classifier: Intended Audience :: Science/Research
Classifier: Operating System :: OS Independent
Classifier: Programming Language :: Python
Classifier: Programming Language :: Python :: 3
Classifier: Programming Language :: Python :: 3 :: Only
Classifier: Programming Language :: Python :: 3.10
Classifier: Programming Language :: Python :: 3.11
Classifier: Topic :: Scientific/Engineering :: Mathematics
Classifier: Topic :: Software Development
Classifier: Topic :: Software Development :: Libraries
Classifier: Topic :: Software Development :: Libraries :: Python Modules
Classifier: Typing :: Typed
Requires-Python: >=3.10
Provides-Extra: all
Requires-Dist: cplex>=20.1.0.4; extra == 'all'
Requires-Dist: docplex>=2.24.231; extra == 'all'
Requires-Dist: gurobipy>=10.0.0; extra == 'all'
Requires-Dist: ortools>=9.6.2534; extra == 'all'
Requires-Dist: pulp>=2.7.0; extra == 'all'
Provides-Extra: cplex
Requires-Dist: cplex>=20.1.0.4; extra == 'cplex'
Requires-Dist: docplex>=2.24.231; extra == 'cplex'
Provides-Extra: dev
Requires-Dist: black>=23.12.0; extra == 'dev'
Requires-Dist: coverage[toml]>=7.3.3; extra == 'dev'
Requires-Dist: cplex>=20.1.0.4; extra == 'dev'
Requires-Dist: docplex>=2.24.231; extra == 'dev'
Requires-Dist: gurobipy>=10.0.0; extra == 'dev'
Requires-Dist: hatch>=1.8.1; extra == 'dev'
Requires-Dist: mkdocs-git-committers-plugin-2>=2.3.0; extra == 'dev'
Requires-Dist: mkdocs-git-revision-date-localized-plugin>=1.2.1; extra == 'dev'
Requires-Dist: mkdocs-material>=9.5.17; extra == 'dev'
Requires-Dist: mkdocs-material[imaging]; extra == 'dev'
Requires-Dist: mkdocstrings[python]>=0.24.0; extra == 'dev'
Requires-Dist: mypy>=1.7.1; extra == 'dev'
Requires-Dist: ortools>=9.6.2534; extra == 'dev'
Requires-Dist: pulp>=2.7.0; extra == 'dev'
Requires-Dist: pytest>=7.4.0; extra == 'dev'
Provides-Extra: docs
Requires-Dist: mkdocs-git-committers-plugin-2>=2.3.0; extra == 'docs'
Requires-Dist: mkdocs-git-revision-date-localized-plugin>=1.2.1; extra == 'docs'
Requires-Dist: mkdocs-material>=9.5.17; extra == 'docs'
Requires-Dist: mkdocs-material[imaging]; extra == 'docs'
Requires-Dist: mkdocstrings[python]>=0.24.0; extra == 'docs'
Provides-Extra: gurobi
Requires-Dist: gurobipy>=10.0.0; extra == 'gurobi'
Provides-Extra: ortools
Requires-Dist: ortools>=9.6.2534; extra == 'ortools'
Provides-Extra: pulp
Requires-Dist: pulp>=2.7.0; extra == 'pulp'
Provides-Extra: tests
Requires-Dist: black>=23.12.0; extra == 'tests'
Requires-Dist: coverage[toml]>=7.3.3; extra == 'tests'
Requires-Dist: cplex>=20.1.0.4; extra == 'tests'
Requires-Dist: docplex>=2.24.231; extra == 'tests'
Requires-Dist: gurobipy>=10.0.0; extra == 'tests'
Requires-Dist: mypy>=1.7.1; extra == 'tests'
Requires-Dist: ortools>=9.6.2534; extra == 'tests'
Requires-Dist: pulp>=2.7.0; extra == 'tests'
Requires-Dist: pytest>=7.4.0; extra == 'tests'
